osn_windows_cmd/__init__.py
osn_windows_cmd/errors.py
osn_windows_cmd/utilities.py
osn_windows_cmd/netstat/__init__.py
osn_windows_cmd/netstat/command.py
osn_windows_cmd/shutdown/__init__.py
osn_windows_cmd/shutdown/command.py
osn_windows_cmd/shutdown/parameters.py
osn_windows_cmd/taskkill/__init__.py
osn_windows_cmd/taskkill/command.py
osn_windows_cmd/taskkill/parameters.py
osn_windows_cmd-1.1.0.dist-info/METADATA
osn_windows_cmd-1.1.0.dist-info/WHEEL
osn_windows_cmd-1.1.0.dist-info/top_level.txt
osn_windows_cmd-1.1.0.dist-info/RECORD
