Metadata-Version: 2.4
Name: osn-windows-cmd
Version: 1.1.0
Summary: osn-windows-cmd is a Python library to simplify working with Windows command-line utilities like `netstat`, `shutdown`, and `taskkill`, providing structured output and a convenient interface.
Author: oddshellnick
Author-email: oddshellnick.programming@gmail.com
Requires-Dist: setuptools>=75.1.0
Requires-Dist: pandas>=2.2.3
Requires-Dist: osn-var-tools>=1.0.0
Dynamic: author
Dynamic: author-email
Dynamic: description
Dynamic: description-content-type
Dynamic: requires-dist
Dynamic: summary
